kedro_wings/__init__.py
kedro_wings/kedro_wings.py
kedro_wings/wing_info.py
kedro_wings-0.2.6.dist-info/LICENSE
kedro_wings-0.2.6.dist-info/METADATA
kedro_wings-0.2.6.dist-info/WHEEL
kedro_wings-0.2.6.dist-info/top_level.txt
kedro_wings-0.2.6.dist-info/RECORD
