Metadata-Version: 2.1
Name: kedro-wings
Version: 0.2.6
Summary: Kedro Wings automatically creates catalog entries to simplify Kedro pipeline writing.
Home-page: https://github.com/tamsanh/kedro-wings.git
Author: Tam-Sanh Nguyen
Author-email: tamsanh@gmail.com
License: MIT
Platform: UNKNOWN
Classifier: License :: OSI Approved :: MIT License
Classifier: Programming Language :: Python :: 3.8
Requires-Dist: kedro (>=0.16.0)
